Metadata-Version: 1.0
Name: roi-cli
Version: 1.4.2
Summary: roi-cli
Home-page: UNKNOWN
Author: wusir
Author-email: wusir666666@163.com
License: MIT Licence
Keywords: pip,os,cli
Platform: any
